wsmsg/__init__.py
wsmsg/__main__.py
wsmsg/client.py
wsmsg/common.py
wsmsg/server.py
wsmsg-0.17.dist-info/LICENSE
wsmsg-0.17.dist-info/METADATA
wsmsg-0.17.dist-info/WHEEL
wsmsg-0.17.dist-info/top_level.txt
wsmsg-0.17.dist-info/RECORD
